fmm2dpy-0.0.5.dist-info/RECORD
fmm2dpy-0.0.5.dist-info/WHEEL
fmm2dpy-0.0.5.dist-info/top_level.txt
fmm2dpy-0.0.5.dist-info/METADATA
fmm2dpy/__init__.py
fmm2dpy/hfmm2d_fortran.cpython-310-darwin.so
fmm2dpy/fmm2d.py
fmm2dpy/lfmm2d_fortran.cpython-310-darwin.so
fmm2dpy/bhfmm2d_fortran.cpython-310-darwin.so
fmm2dpy/.dylibs/libgfortran.5.dylib
fmm2dpy/.dylibs/libquadmath.0.dylib
fmm2dpy/.dylibs/libgcc_s.1.1.dylib
fmm2dpy/.dylibs/libgomp.1.dylib
