Metadata-Version: 2.1
Name: fmm2dpy
Version: 0.0.5
Summary: This pacakge contains basic routines for Laplace and Helmholtz fast multipole methods in two dimensions
Home-page: 
Author: Travis Askham, Zydrunas Gimbutas, Leslie Greengard, Libin Lu, Michael O'Neil, Manas Rachh, and Vladimir Rokhlin
Author-email: mrachh@flatironinstitute.org
Classifier: Programming Language :: Python :: 3
Classifier: License :: OSI Approved :: Apache Software License
Classifier: Operating System :: OS Independent
Requires-Python: >=3.0.0
Requires-Dist: numpy
Requires-Dist: pytest
